givemedata/__init__.py
givemedata/givemedata.py
givemedata/version.py
givemedata/tests/__init__.py
givemedata/tests/test_cassandra.py
givemedata/utils/__init__.py
givemedata/utils/common.py
givemedata/utils/pandas.py
givemedata-0.4.0.dist-info/LICENSE
givemedata-0.4.0.dist-info/METADATA
givemedata-0.4.0.dist-info/WHEEL
givemedata-0.4.0.dist-info/entry_points.txt
givemedata-0.4.0.dist-info/top_level.txt
givemedata-0.4.0.dist-info/RECORD
