Metadata-Version: 2.1
Name: givemedata
Version: 0.4.0
Summary: A convenient way to use and explore multiple databases from Python.
Home-page: https://github.com/sancau/givemedata/
Author: Alexander Tatchin
Author-email: alexander.tatchin@gmail.com
License: MIT
Platform: any
Classifier: Development Status :: 3 - Alpha
Classifier: Intended Audience :: Developers
Classifier: Intended Audience :: Information Technology
Classifier: Intended Audience :: Science/Research
Classifier: Intended Audience :: System Administrators
Classifier: License :: OSI Approved :: MIT License
Classifier: Operating System :: POSIX
Classifier: Operating System :: MacOS
Classifier: Operating System :: Unix
Classifier: Programming Language :: Python :: 3
Classifier: Topic :: Software Development :: Libraries :: Python Modules
Classifier: Topic :: Scientific/Engineering
Requires-Dist: pandas (>=0.24.2)
Requires-Dist: SQLAlchemy (>=1.3.3)
Requires-Dist: pyyaml (>=5.1)
Requires-Dist: psycopg2-binary (>=2.8.4)
